MANIFEST.in
README.txt
setup.py
docs/HISTORY.txt
docs/LICENSE.txt
src/silva/__init__.py
src/silva.core.editor.egg-info/PKG-INFO
src/silva.core.editor.egg-info/SOURCES.txt
src/silva.core.editor.egg-info/dependency_links.txt
src/silva.core.editor.egg-info/entry_points.txt
src/silva.core.editor.egg-info/namespace_packages.txt
src/silva.core.editor.egg-info/not-zip-safe
src/silva.core.editor.egg-info/requires.txt
src/silva.core.editor.egg-info/top_level.txt
src/silva/core/__init__.py
src/silva/core/editor/__init__.py
src/silva/core/editor/configure.zcml
src/silva/core/editor/ftesting.zcml
src/silva/core/editor/interfaces.py
src/silva/core/editor/service.png
src/silva/core/editor/service.py
src/silva/core/editor/templates.py
src/silva/core/editor/testing.py
src/silva/core/editor/text.py
src/silva/core/editor/utils.py
src/silva/core/editor/static/broken-link.jpg
src/silva/core/editor/static/content.css
src/silva/core/editor/static/content.min.css
src/silva/core/editor/static/editor.js
src/silva/core/editor/static/editor.min.js
src/silva/core/editor/static/plugins/silvaanchor/plugin.js
src/silva/core/editor/static/plugins/silvaanchor/dialogs/anchor.js
src/silva/core/editor/static/plugins/silvadialog/plugin.js
src/silva/core/editor/static/plugins/silvaformat/plugin.js
src/silva/core/editor/static/plugins/silvaimage/plugin.js
src/silva/core/editor/static/plugins/silvaimage/dialogs/image.js
src/silva/core/editor/static/plugins/silvalink/plugin.js
src/silva/core/editor/static/plugins/silvalink/dialogs/link.js
src/silva/core/editor/static/plugins/silvasave/plugin.js
src/silva/core/editor/static/plugins/silvatablestyles/plugin.js
src/silva/core/editor/static/plugins/silvautils/plugin.js
src/silva/core/editor/static/skins/silva/dialog.css
src/silva/core/editor/static/skins/silva/editor.css
src/silva/core/editor/static/skins/silva/icons.png
src/silva/core/editor/static/skins/silva/skin.js
src/silva/core/editor/static/skins/silva/templates.css
src/silva/core/editor/static/skins/silva/images/dialog_sides.gif
src/silva/core/editor/static/skins/silva/images/dialog_sides.png
src/silva/core/editor/static/skins/silva/images/dialog_top_gradient.png
src/silva/core/editor/static/skins/silva/images/gradient.png
src/silva/core/editor/static/skins/silva/images/mini.gif
src/silva/core/editor/static/skins/silva/images/noimage.png
