Metadata-Version: 1.1
Name: silva.core.editor
Version: 3.0.3
Summary: Support for the WYSIWYG editor CKEditor in the Silva CMS
Home-page: https://github.com/silvacms/silva.core.editor
Author: Infrae
Author-email: info@infrae.com
License: BSD
Keywords: silva core editor wysiwyg ckeditor
Platform: UNKNOWN
Classifier: Framework :: Zope2
Classifier: License :: OSI Approved :: BSD License
Classifier: Programming Language :: Python
Classifier: Topic :: Software Development :: Libraries :: Python Modules
